gridsculpt/__init__.py
gridsculpt/gridsculpt.py
gridsculpt/py.typed
gridsculpt/version.py
gridsculpt-0.1.4.dist-info/LICENSE
gridsculpt-0.1.4.dist-info/METADATA
gridsculpt-0.1.4.dist-info/WHEEL
gridsculpt-0.1.4.dist-info/top_level.txt
gridsculpt-0.1.4.dist-info/RECORD
